[
  {
    "ContainingType": "Legno.WebApi.Controllers.AdminsController",
    "Method": "Login",
    "RelativePath": "api/Admins/login",
    "HttpMethod": "POST",
    "IsController": true,
    "Order": 0,
    "Parameters": [
      {
        "Name": "loginDto",
        "Type": "Legno.Application.Dtos.Account.LoginDto",
        "IsRequired": true
      }
    ],
    "ReturnTypes": []
  },
  {
    "ContainingType": "Legno.WebApi.Controllers.B2BServicesController",
    "Method": "Create",
    "RelativePath": "api/B2BServices/create",
    "HttpMethod": "POST",
    "IsController": true,
    "Order": 0,
    "Parameters": [
      {
        "Name": "dto",
        "Type": "Legno.Application.Dtos.CommonService.CreateCommonServiceDto",
        "IsRequired": true
      }
    ],
    "ReturnTypes": []
  },
  {
    "ContainingType": "Legno.WebApi.Controllers.B2BServicesController",
    "Method": "Delete",
    "RelativePath": "api/B2BServices/delete/{id}",
    "HttpMethod": "DELETE",
    "IsController": true,
    "Order": 0,
    "Parameters": [
      {
        "Name": "id",
        "Type": "System.String",
        "IsRequired": true
      }
    ],
    "ReturnTypes": []
  },
  {
    "ContainingType": "Legno.WebApi.Controllers.B2BServicesController",
    "Method": "GetAll",
    "RelativePath": "api/B2BServices/get-all",
    "HttpMethod": "GET",
    "IsController": true,
    "Order": 0,
    "Parameters": [],
    "ReturnTypes": []
  },
  {
    "ContainingType": "Legno.WebApi.Controllers.B2BServicesController",
    "Method": "Get",
    "RelativePath": "api/B2BServices/get/{id}",
    "HttpMethod": "GET",
    "IsController": true,
    "Order": 0,
    "Parameters": [
      {
        "Name": "id",
        "Type": "System.String",
        "IsRequired": true
      }
    ],
    "ReturnTypes": []
  },
  {
    "ContainingType": "Legno.WebApi.Controllers.B2BServicesController",
    "Method": "Update",
    "RelativePath": "api/B2BServices/update",
    "HttpMethod": "PUT",
    "IsController": true,
    "Order": 0,
    "Parameters": [
      {
        "Name": "dto",
        "Type": "Legno.Application.Dtos.CommonService.UpdateCommonServiceDto",
        "IsRequired": true
      }
    ],
    "ReturnTypes": []
  },
  {
    "ContainingType": "Legno.Api.Controllers.BlogsController",
    "Method": "CreateBlog",
    "RelativePath": "api/Blogs/create-blog",
    "HttpMethod": "POST",
    "IsController": true,
    "Order": 0,
    "Parameters": [
      {
        "Name": "Title",
        "Type": "System.String",
        "IsRequired": false
      },
      {
        "Name": "TitleEng",
        "Type": "System.String",
        "IsRequired": false
      },
      {
        "Name": "TitleRu",
        "Type": "System.String",
        "IsRequired": false
      },
      {
        "Name": "SubTitle",
        "Type": "System.String",
        "IsRequired": false
      },
      {
        "Name": "SubTitleEng",
        "Type": "System.String",
        "IsRequired": false
      },
      {
        "Name": "SubTitleRu",
        "Type": "System.String",
        "IsRequired": false
      },
      {
        "Name": "BlogImage",
        "Type": "Microsoft.AspNetCore.Http.IFormFile",
        "IsRequired": false
      },
      {
        "Name": "AuthorName",
        "Type": "System.String",
        "IsRequired": false
      },
      {
        "Name": "AuthorNameEng",
        "Type": "System.String",
        "IsRequired": false
      },
      {
        "Name": "AuthorNameRu",
        "Type": "System.String",
        "IsRequired": false
      },
      {
        "Name": "AuthorProfession",
        "Type": "System.String",
        "IsRequired": false
      },
      {
        "Name": "AuthorImage",
        "Type": "Microsoft.AspNetCore.Http.IFormFile",
        "IsRequired": false
      }
    ],
    "ReturnTypes": []
  },
  {
    "ContainingType": "Legno.Api.Controllers.BlogsController",
    "Method": "DeleteBlog",
    "RelativePath": "api/Blogs/delete-blog/{blogId}",
    "HttpMethod": "DELETE",
    "IsController": true,
    "Order": 0,
    "Parameters": [
      {
        "Name": "blogId",
        "Type": "System.String",
        "IsRequired": true
      }
    ],
    "ReturnTypes": []
  },
  {
    "ContainingType": "Legno.Api.Controllers.BlogsController",
    "Method": "GetAllBlogs",
    "RelativePath": "api/Blogs/get-all-blogs",
    "HttpMethod": "GET",
    "IsController": true,
    "Order": 0,
    "Parameters": [],
    "ReturnTypes": []
  },
  {
    "ContainingType": "Legno.Api.Controllers.BlogsController",
    "Method": "GetBlog",
    "RelativePath": "api/Blogs/get-blog/{blogId}",
    "HttpMethod": "GET",
    "IsController": true,
    "Order": 0,
    "Parameters": [
      {
        "Name": "blogId",
        "Type": "System.String",
        "IsRequired": true
      }
    ],
    "ReturnTypes": []
  },
  {
    "ContainingType": "Legno.Api.Controllers.BlogsController",
    "Method": "UpdateBlog",
    "RelativePath": "api/Blogs/update-blog",
    "HttpMethod": "PUT",
    "IsController": true,
    "Order": 0,
    "Parameters": [
      {
        "Name": "Id",
        "Type": "System.String",
        "IsRequired": false
      },
      {
        "Name": "Title",
        "Type": "System.String",
        "IsRequired": false
      },
      {
        "Name": "TitleEng",
        "Type": "System.String",
        "IsRequired": false
      },
      {
        "Name": "TitleRu",
        "Type": "System.String",
        "IsRequired": false
      },
      {
        "Name": "SubTitle",
        "Type": "System.String",
        "IsRequired": false
      },
      {
        "Name": "SubTitleEng",
        "Type": "System.String",
        "IsRequired": false
      },
      {
        "Name": "SubTitleRu",
        "Type": "System.String",
        "IsRequired": false
      },
      {
        "Name": "BlogImage",
        "Type": "Microsoft.AspNetCore.Http.IFormFile",
        "IsRequired": false
      },
      {
        "Name": "AuthorName",
        "Type": "System.String",
        "IsRequired": false
      },
      {
        "Name": "AuthorNameEng",
        "Type": "System.String",
        "IsRequired": false
      },
      {
        "Name": "AuthorNameRu",
        "Type": "System.String",
        "IsRequired": false
      },
      {
        "Name": "AuthorProfession",
        "Type": "System.String",
        "IsRequired": false
      },
      {
        "Name": "AuthorImage",
        "Type": "Microsoft.AspNetCore.Http.IFormFile",
        "IsRequired": false
      }
    ],
    "ReturnTypes": []
  },
  {
    "ContainingType": "Legno.Api.Controllers.BusinessServicesController",
    "Method": "Create",
    "RelativePath": "api/BusinessServices/create",
    "HttpMethod": "POST",
    "IsController": true,
    "Order": 0,
    "Parameters": [
      {
        "Name": "Name",
        "Type": "System.String",
        "IsRequired": false
      },
      {
        "Name": "NameEng",
        "Type": "System.String",
        "IsRequired": false
      },
      {
        "Name": "NameRu",
        "Type": "System.String",
        "IsRequired": false
      },
      {
        "Name": "CardImage",
        "Type": "Microsoft.AspNetCore.Http.IFormFile",
        "IsRequired": false
      }
    ],
    "ReturnTypes": []
  },
  {
    "ContainingType": "Legno.Api.Controllers.BusinessServicesController",
    "Method": "Delete",
    "RelativePath": "api/BusinessServices/delete/{BusinessServiceId}",
    "HttpMethod": "DELETE",
    "IsController": true,
    "Order": 0,
    "Parameters": [
      {
        "Name": "BusinessServiceId",
        "Type": "System.String",
        "IsRequired": true
      }
    ],
    "ReturnTypes": []
  },
  {
    "ContainingType": "Legno.Api.Controllers.BusinessServicesController",
    "Method": "GetAll",
    "RelativePath": "api/BusinessServices/get-all",
    "HttpMethod": "GET",
    "IsController": true,
    "Order": 0,
    "Parameters": [],
    "ReturnTypes": []
  },
  {
    "ContainingType": "Legno.Api.Controllers.BusinessServicesController",
    "Method": "Get",
    "RelativePath": "api/BusinessServices/get/{BusinessServiceId}",
    "HttpMethod": "GET",
    "IsController": true,
    "Order": 0,
    "Parameters": [
      {
        "Name": "BusinessServiceId",
        "Type": "System.String",
        "IsRequired": true
      }
    ],
    "ReturnTypes": []
  },
  {
    "ContainingType": "Legno.Api.Controllers.BusinessServicesController",
    "Method": "Update",
    "RelativePath": "api/BusinessServices/update",
    "HttpMethod": "PUT",
    "IsController": true,
    "Order": 0,
    "Parameters": [
      {
        "Name": "Id",
        "Type": "System.String",
        "IsRequired": false
      },
      {
        "Name": "Name",
        "Type": "System.String",
        "IsRequired": false
      },
      {
        "Name": "NameEng",
        "Type": "System.String",
        "IsRequired": false
      },
      {
        "Name": "NameRu",
        "Type": "System.String",
        "IsRequired": false
      },
      {
        "Name": "CardImage",
        "Type": "Microsoft.AspNetCore.Http.IFormFile",
        "IsRequired": false
      }
    ],
    "ReturnTypes": []
  },
  {
    "ContainingType": "Legno.Api.Controllers.CategoriesController",
    "Method": "Create",
    "RelativePath": "api/Categories/create",
    "HttpMethod": "POST",
    "IsController": true,
    "Order": 0,
    "Parameters": [
      {
        "Name": "Name",
        "Type": "System.String",
        "IsRequired": false
      },
      {
        "Name": "NameRu",
        "Type": "System.String",
        "IsRequired": false
      },
      {
        "Name": "NameEng",
        "Type": "System.String",
        "IsRequired": false
      },
      {
        "Name": "CategoryImage",
        "Type": "Microsoft.AspNetCore.Http.IFormFile",
        "IsRequired": false
      }
    ],
    "ReturnTypes": []
  },
  {
    "ContainingType": "Legno.Api.Controllers.CategoriesController",
    "Method": "Delete",
    "RelativePath": "api/Categories/delete/{id}",
    "HttpMethod": "DELETE",
    "IsController": true,
    "Order": 0,
    "Parameters": [
      {
        "Name": "id",
        "Type": "System.String",
        "IsRequired": true
      }
    ],
    "ReturnTypes": []
  },
  {
    "ContainingType": "Legno.Api.Controllers.CategoriesController",
    "Method": "GetAll",
    "RelativePath": "api/Categories/get-all",
    "HttpMethod": "GET",
    "IsController": true,
    "Order": 0,
    "Parameters": [],
    "ReturnTypes": []
  },
  {
    "ContainingType": "Legno.Api.Controllers.CategoriesController",
    "Method": "Get",
    "RelativePath": "api/Categories/get/{id}",
    "HttpMethod": "GET",
    "IsController": true,
    "Order": 0,
    "Parameters": [
      {
        "Name": "id",
        "Type": "System.String",
        "IsRequired": true
      }
    ],
    "ReturnTypes": []
  },
  {
    "ContainingType": "Legno.Api.Controllers.CategoriesController",
    "Method": "Update",
    "RelativePath": "api/Categories/update",
    "HttpMethod": "PUT",
    "IsController": true,
    "Order": 0,
    "Parameters": [
      {
        "Name": "Id",
        "Type": "System.String",
        "IsRequired": false
      },
      {
        "Name": "Name",
        "Type": "System.String",
        "IsRequired": false
      },
      {
        "Name": "NameRu",
        "Type": "System.String",
        "IsRequired": false
      },
      {
        "Name": "NameEng",
        "Type": "System.String",
        "IsRequired": false
      },
      {
        "Name": "CategoryImage",
        "Type": "Microsoft.AspNetCore.Http.IFormFile",
        "IsRequired": false
      }
    ],
    "ReturnTypes": []
  },
  {
    "ContainingType": "Legno.Api.Controllers.CommonServicesController",
    "Method": "Create",
    "RelativePath": "api/CommonServices/create",
    "HttpMethod": "POST",
    "IsController": true,
    "Order": 0,
    "Parameters": [
      {
        "Name": "dto",
        "Type": "Legno.Application.Dtos.CommonService.CreateCommonServiceDto",
        "IsRequired": true
      }
    ],
    "ReturnTypes": []
  },
  {
    "ContainingType": "Legno.Api.Controllers.CommonServicesController",
    "Method": "Delete",
    "RelativePath": "api/CommonServices/delete/{id}",
    "HttpMethod": "DELETE",
    "IsController": true,
    "Order": 0,
    "Parameters": [
      {
        "Name": "id",
        "Type": "System.String",
        "IsRequired": true
      }
    ],
    "ReturnTypes": []
  },
  {
    "ContainingType": "Legno.Api.Controllers.CommonServicesController",
    "Method": "GetAll",
    "RelativePath": "api/CommonServices/get-all",
    "HttpMethod": "GET",
    "IsController": true,
    "Order": 0,
    "Parameters": [],
    "ReturnTypes": []
  },
  {
    "ContainingType": "Legno.Api.Controllers.CommonServicesController",
    "Method": "Get",
    "RelativePath": "api/CommonServices/get/{id}",
    "HttpMethod": "GET",
    "IsController": true,
    "Order": 0,
    "Parameters": [
      {
        "Name": "id",
        "Type": "System.String",
        "IsRequired": true
      }
    ],
    "ReturnTypes": []
  },
  {
    "ContainingType": "Legno.Api.Controllers.CommonServicesController",
    "Method": "Update",
    "RelativePath": "api/CommonServices/update",
    "HttpMethod": "PUT",
    "IsController": true,
    "Order": 0,
    "Parameters": [
      {
        "Name": "dto",
        "Type": "Legno.Application.Dtos.CommonService.UpdateCommonServiceDto",
        "IsRequired": true
      }
    ],
    "ReturnTypes": []
  },
  {
    "ContainingType": "Legno.Api.Controllers.ContactsController",
    "Method": "GetContactById",
    "RelativePath": "api/Contacts/contact/{id}",
    "HttpMethod": "GET",
    "IsController": true,
    "Order": 0,
    "Parameters": [
      {
        "Name": "id",
        "Type": "System.String",
        "IsRequired": true
      }
    ],
    "ReturnTypes": []
  },
  {
    "ContainingType": "Legno.Api.Controllers.ContactsController",
    "Method": "CreateContact",
    "RelativePath": "api/Contacts/create-contact",
    "HttpMethod": "POST",
    "IsController": true,
    "Order": 0,
    "Parameters": [
      {
        "Name": "createContactDto",
        "Type": "Legno.Application.Dtos.Contact.CreateContactDto",
        "IsRequired": true
      }
    ],
    "ReturnTypes": []
  },
  {
    "ContainingType": "Legno.Api.Controllers.ContactsController",
    "Method": "GetAllContacts",
    "RelativePath": "api/Contacts/get-all-contacts",
    "HttpMethod": "GET",
    "IsController": true,
    "Order": 0,
    "Parameters": [],
    "ReturnTypes": []
  },
  {
    "ContainingType": "Legno.Api.Controllers.DesignerCommonServicesController",
    "Method": "Create",
    "RelativePath": "api/DesignerCommonServices/create",
    "HttpMethod": "POST",
    "IsController": true,
    "Order": 0,
    "Parameters": [
      {
        "Name": "Title",
        "Type": "System.String",
        "IsRequired": false
      },
      {
        "Name": "TitleEng",
        "Type": "System.String",
        "IsRequired": false
      },
      {
        "Name": "TitleRu",
        "Type": "System.String",
        "IsRequired": false
      },
      {
        "Name": "SubTitle",
        "Type": "System.String",
        "IsRequired": false
      },
      {
        "Name": "SubTitleEng",
        "Type": "System.String",
        "IsRequired": false
      },
      {
        "Name": "SubTitleRu",
        "Type": "System.String",
        "IsRequired": false
      },
      {
        "Name": "CardImage",
        "Type": "Microsoft.AspNetCore.Http.IFormFile",
        "IsRequired": false
      }
    ],
    "ReturnTypes": []
  },
  {
    "ContainingType": "Legno.Api.Controllers.DesignerCommonServicesController",
    "Method": "Delete",
    "RelativePath": "api/DesignerCommonServices/delete/{designerCommonServiceId}",
    "HttpMethod": "DELETE",
    "IsController": true,
    "Order": 0,
    "Parameters": [
      {
        "Name": "designerCommonServiceId",
        "Type": "System.String",
        "IsRequired": true
      }
    ],
    "ReturnTypes": []
  },
  {
    "ContainingType": "Legno.Api.Controllers.DesignerCommonServicesController",
    "Method": "GetAll",
    "RelativePath": "api/DesignerCommonServices/get-all",
    "HttpMethod": "GET",
    "IsController": true,
    "Order": 0,
    "Parameters": [],
    "ReturnTypes": []
  },
  {
    "ContainingType": "Legno.Api.Controllers.DesignerCommonServicesController",
    "Method": "Get",
    "RelativePath": "api/DesignerCommonServices/get/{designerCommonServiceId}",
    "HttpMethod": "GET",
    "IsController": true,
    "Order": 0,
    "Parameters": [
      {
        "Name": "designerCommonServiceId",
        "Type": "System.String",
        "IsRequired": true
      }
    ],
    "ReturnTypes": []
  },
  {
    "ContainingType": "Legno.Api.Controllers.DesignerCommonServicesController",
    "Method": "Update",
    "RelativePath": "api/DesignerCommonServices/update",
    "HttpMethod": "PUT",
    "IsController": true,
    "Order": 0,
    "Parameters": [
      {
        "Name": "Id",
        "Type": "System.String",
        "IsRequired": false
      },
      {
        "Name": "Title",
        "Type": "System.String",
        "IsRequired": false
      },
      {
        "Name": "TitleEng",
        "Type": "System.String",
        "IsRequired": false
      },
      {
        "Name": "TitleRu",
        "Type": "System.String",
        "IsRequired": false
      },
      {
        "Name": "SubTitle",
        "Type": "System.String",
        "IsRequired": false
      },
      {
        "Name": "SubTitleEng",
        "Type": "System.String",
        "IsRequired": false
      },
      {
        "Name": "SubTitleRu",
        "Type": "System.String",
        "IsRequired": false
      },
      {
        "Name": "CardImage",
        "Type": "Microsoft.AspNetCore.Http.IFormFile",
        "IsRequired": false
      }
    ],
    "ReturnTypes": []
  },
  {
    "ContainingType": "Legno.WebApi.Controllers.DesignerServicesController",
    "Method": "Create",
    "RelativePath": "api/DesignerServices/create",
    "HttpMethod": "POST",
    "IsController": true,
    "Order": 0,
    "Parameters": [
      {
        "Name": "Name",
        "Type": "System.String",
        "IsRequired": false
      },
      {
        "Name": "NameEng",
        "Type": "System.String",
        "IsRequired": false
      },
      {
        "Name": "NameRu",
        "Type": "System.String",
        "IsRequired": false
      },
      {
        "Name": "CardImage",
        "Type": "Microsoft.AspNetCore.Http.IFormFile",
        "IsRequired": false
      }
    ],
    "ReturnTypes": []
  },
  {
    "ContainingType": "Legno.WebApi.Controllers.DesignerServicesController",
    "Method": "Delete",
    "RelativePath": "api/DesignerServices/delete/{BusinessServiceId}",
    "HttpMethod": "DELETE",
    "IsController": true,
    "Order": 0,
    "Parameters": [
      {
        "Name": "BusinessServiceId",
        "Type": "System.String",
        "IsRequired": true
      }
    ],
    "ReturnTypes": []
  },
  {
    "ContainingType": "Legno.WebApi.Controllers.DesignerServicesController",
    "Method": "GetAll",
    "RelativePath": "api/DesignerServices/get-all",
    "HttpMethod": "GET",
    "IsController": true,
    "Order": 0,
    "Parameters": [],
    "ReturnTypes": []
  },
  {
    "ContainingType": "Legno.WebApi.Controllers.DesignerServicesController",
    "Method": "Get",
    "RelativePath": "api/DesignerServices/get/{BusinessServiceId}",
    "HttpMethod": "GET",
    "IsController": true,
    "Order": 0,
    "Parameters": [
      {
        "Name": "BusinessServiceId",
        "Type": "System.String",
        "IsRequired": true
      }
    ],
    "ReturnTypes": []
  },
  {
    "ContainingType": "Legno.WebApi.Controllers.DesignerServicesController",
    "Method": "Update",
    "RelativePath": "api/DesignerServices/update",
    "HttpMethod": "PUT",
    "IsController": true,
    "Order": 0,
    "Parameters": [
      {
        "Name": "Id",
        "Type": "System.String",
        "IsRequired": false
      },
      {
        "Name": "Name",
        "Type": "System.String",
        "IsRequired": false
      },
      {
        "Name": "NameEng",
        "Type": "System.String",
        "IsRequired": false
      },
      {
        "Name": "NameRu",
        "Type": "System.String",
        "IsRequired": false
      },
      {
        "Name": "CardImage",
        "Type": "Microsoft.AspNetCore.Http.IFormFile",
        "IsRequired": false
      }
    ],
    "ReturnTypes": []
  },
  {
    "ContainingType": "Legno.Api.Controllers.FabricsController",
    "Method": "Delete",
    "RelativePath": "api/Fabrics/delete/{fabricId}",
    "HttpMethod": "DELETE",
    "IsController": true,
    "Order": 0,
    "Parameters": [
      {
        "Name": "fabricId",
        "Type": "System.String",
        "IsRequired": true
      }
    ],
    "ReturnTypes": []
  },
  {
    "ContainingType": "Legno.Api.Controllers.FabricsController",
    "Method": "GetAll",
    "RelativePath": "api/Fabrics/get-all",
    "HttpMethod": "GET",
    "IsController": true,
    "Order": 0,
    "Parameters": [],
    "ReturnTypes": []
  },
  {
    "ContainingType": "Legno.Api.Controllers.FabricsController",
    "Method": "Get",
    "RelativePath": "api/Fabrics/get/{fabricId}",
    "HttpMethod": "GET",
    "IsController": true,
    "Order": 0,
    "Parameters": [
      {
        "Name": "fabricId",
        "Type": "System.String",
        "IsRequired": true
      }
    ],
    "ReturnTypes": []
  },
  {
    "ContainingType": "Legno.Api.Controllers.FabricsController",
    "Method": "Upload",
    "RelativePath": "api/Fabrics/upload",
    "HttpMethod": "POST",
    "IsController": true,
    "Order": 0,
    "Parameters": [
      {
        "Name": "fabricName",
        "Type": "Microsoft.AspNetCore.Http.IFormFile",
        "IsRequired": false
      }
    ],
    "ReturnTypes": []
  },
  {
    "ContainingType": "Legno.Api.Controllers.FAQsController",
    "Method": "Create",
    "RelativePath": "api/FAQs/create",
    "HttpMethod": "POST",
    "IsController": true,
    "Order": 0,
    "Parameters": [
      {
        "Name": "dto",
        "Type": "Legno.Application.Dtos.FAQ.CreateFAQDto",
        "IsRequired": true
      }
    ],
    "ReturnTypes": []
  },
  {
    "ContainingType": "Legno.Api.Controllers.FAQsController",
    "Method": "Delete",
    "RelativePath": "api/FAQs/delete/{id}",
    "HttpMethod": "DELETE",
    "IsController": true,
    "Order": 0,
    "Parameters": [
      {
        "Name": "id",
        "Type": "System.String",
        "IsRequired": true
      }
    ],
    "ReturnTypes": []
  },
  {
    "ContainingType": "Legno.Api.Controllers.FAQsController",
    "Method": "GetAll",
    "RelativePath": "api/FAQs/get-all",
    "HttpMethod": "GET",
    "IsController": true,
    "Order": 0,
    "Parameters": [],
    "ReturnTypes": []
  },
  {
    "ContainingType": "Legno.Api.Controllers.FAQsController",
    "Method": "Get",
    "RelativePath": "api/FAQs/get/{id}",
    "HttpMethod": "GET",
    "IsController": true,
    "Order": 0,
    "Parameters": [
      {
        "Name": "id",
        "Type": "System.String",
        "IsRequired": true
      }
    ],
    "ReturnTypes": []
  },
  {
    "ContainingType": "Legno.Api.Controllers.FAQsController",
    "Method": "Update",
    "RelativePath": "api/FAQs/update",
    "HttpMethod": "PUT",
    "IsController": true,
    "Order": 0,
    "Parameters": [
      {
        "Name": "dto",
        "Type": "Legno.Application.Dtos.FAQ.UpdateFAQDto",
        "IsRequired": true
      }
    ],
    "ReturnTypes": []
  },
  {
    "ContainingType": "Legno.Api.Controllers.LocationsController",
    "Method": "Create",
    "RelativePath": "api/Locations/create",
    "HttpMethod": "POST",
    "IsController": true,
    "Order": 0,
    "Parameters": [
      {
        "Name": "dto",
        "Type": "Legno.Application.Dtos.Location.CreateLocationDto",
        "IsRequired": true
      }
    ],
    "ReturnTypes": []
  },
  {
    "ContainingType": "Legno.Api.Controllers.LocationsController",
    "Method": "Delete",
    "RelativePath": "api/Locations/delete/{id}",
    "HttpMethod": "DELETE",
    "IsController": true,
    "Order": 0,
    "Parameters": [
      {
        "Name": "id",
        "Type": "System.String",
        "IsRequired": true
      }
    ],
    "ReturnTypes": []
  },
  {
    "ContainingType": "Legno.Api.Controllers.LocationsController",
    "Method": "GetAll",
    "RelativePath": "api/Locations/get-all",
    "HttpMethod": "GET",
    "IsController": true,
    "Order": 0,
    "Parameters": [],
    "ReturnTypes": []
  },
  {
    "ContainingType": "Legno.Api.Controllers.LocationsController",
    "Method": "Get",
    "RelativePath": "api/Locations/get/{id}",
    "HttpMethod": "GET",
    "IsController": true,
    "Order": 0,
    "Parameters": [
      {
        "Name": "id",
        "Type": "System.String",
        "IsRequired": true
      }
    ],
    "ReturnTypes": []
  },
  {
    "ContainingType": "Legno.Api.Controllers.LocationsController",
    "Method": "Update",
    "RelativePath": "api/Locations/update",
    "HttpMethod": "PUT",
    "IsController": true,
    "Order": 0,
    "Parameters": [
      {
        "Name": "dto",
        "Type": "Legno.Application.Dtos.Location.UpdateLocationDto",
        "IsRequired": true
      }
    ],
    "ReturnTypes": []
  },
  {
    "ContainingType": "Legno.WebApi.Controllers.PartnersController",
    "Method": "Create",
    "RelativePath": "api/Partners/create",
    "HttpMethod": "POST",
    "IsController": true,
    "Order": 0,
    "Parameters": [
      {
        "Name": "Name",
        "Type": "System.String",
        "IsRequired": false
      },
      {
        "Name": "NameEng",
        "Type": "System.String",
        "IsRequired": false
      },
      {
        "Name": "NameRu",
        "Type": "System.String",
        "IsRequired": false
      },
      {
        "Name": "CardImage",
        "Type": "Microsoft.AspNetCore.Http.IFormFile",
        "IsRequired": false
      }
    ],
    "ReturnTypes": []
  },
  {
    "ContainingType": "Legno.WebApi.Controllers.PartnersController",
    "Method": "Delete",
    "RelativePath": "api/Partners/delete/{id}",
    "HttpMethod": "DELETE",
    "IsController": true,
    "Order": 0,
    "Parameters": [
      {
        "Name": "id",
        "Type": "System.String",
        "IsRequired": true
      }
    ],
    "ReturnTypes": []
  },
  {
    "ContainingType": "Legno.WebApi.Controllers.PartnersController",
    "Method": "GetAll",
    "RelativePath": "api/Partners/get-all",
    "HttpMethod": "GET",
    "IsController": true,
    "Order": 0,
    "Parameters": [],
    "ReturnTypes": []
  },
  {
    "ContainingType": "Legno.WebApi.Controllers.PartnersController",
    "Method": "Get",
    "RelativePath": "api/Partners/get/{id}",
    "HttpMethod": "GET",
    "IsController": true,
    "Order": 0,
    "Parameters": [
      {
        "Name": "id",
        "Type": "System.String",
        "IsRequired": true
      }
    ],
    "ReturnTypes": []
  },
  {
    "ContainingType": "Legno.WebApi.Controllers.PartnersController",
    "Method": "Update",
    "RelativePath": "api/Partners/update",
    "HttpMethod": "PUT",
    "IsController": true,
    "Order": 0,
    "Parameters": [
      {
        "Name": "Id",
        "Type": "System.String",
        "IsRequired": false
      },
      {
        "Name": "Name",
        "Type": "System.String",
        "IsRequired": false
      },
      {
        "Name": "NameEng",
        "Type": "System.String",
        "IsRequired": false
      },
      {
        "Name": "NameRu",
        "Type": "System.String",
        "IsRequired": false
      },
      {
        "Name": "CardImage",
        "Type": "Microsoft.AspNetCore.Http.IFormFile",
        "IsRequired": false
      }
    ],
    "ReturnTypes": []
  },
  {
    "ContainingType": "Legno.Api.Controllers.ProjectsController",
    "Method": "GetByCategory",
    "RelativePath": "api/Projects/by-category/{categoryId}",
    "HttpMethod": "GET",
    "IsController": true,
    "Order": 0,
    "Parameters": [
      {
        "Name": "categoryId",
        "Type": "System.String",
        "IsRequired": true
      }
    ],
    "ReturnTypes": []
  },
  {
    "ContainingType": "Legno.Api.Controllers.ProjectsController",
    "Method": "Create",
    "RelativePath": "api/Projects/create",
    "HttpMethod": "POST",
    "IsController": true,
    "Order": 0,
    "Parameters": [
      {
        "Name": "Title",
        "Type": "System.String",
        "IsRequired": false
      },
      {
        "Name": "TitleEng",
        "Type": "System.String",
        "IsRequired": false
      },
      {
        "Name": "TitleRu",
        "Type": "System.String",
        "IsRequired": false
      },
      {
        "Name": "SubTitle",
        "Type": "System.String",
        "IsRequired": false
      },
      {
        "Name": "SubTitleEng",
        "Type": "System.String",
        "IsRequired": false
      },
      {
        "Name": "SubTitleRu",
        "Type": "System.String",
        "IsRequired": false
      },
      {
        "Name": "CardImage",
        "Type": "Microsoft.AspNetCore.Http.IFormFile",
        "IsRequired": false
      },
      {
        "Name": "TeamId",
        "Type": "System.String",
        "IsRequired": false
      },
      {
        "Name": "CategoryId",
        "Type": "System.String",
        "IsRequired": false
      },
      {
        "Name": "ProjectImages",
        "Type": "System.Collections.Generic.List\u00601[[Microsoft.AspNetCore.Http.IFormFile, Microsoft.AspNetCore.Http.Features, Version=8.0.0.0, Culture=neutral, PublicKeyToken=adb9793829ddae60]]",
        "IsRequired": false
      },
      {
        "Name": "ProjectSliderImages",
        "Type": "System.Collections.Generic.List\u00601[[Microsoft.AspNetCore.Http.IFormFile, Microsoft.AspNetCore.Http.Features, Version=8.0.0.0, Culture=neutral, PublicKeyToken=adb9793829ddae60]]",
        "IsRequired": false
      },
      {
        "Name": "ProjectVideos",
        "Type": "System.Collections.Generic.List\u00601[[System.String, System.Private.CoreLib, Version=8.0.0.0, Culture=neutral, PublicKeyToken=7cec85d7bea7798e]]",
        "IsRequired": false
      },
      {
        "Name": "FabricIds",
        "Type": "System.Collections.Generic.List\u00601[[System.String, System.Private.CoreLib, Version=8.0.0.0, Culture=neutral, PublicKeyToken=7cec85d7bea7798e]]",
        "IsRequired": false
      }
    ],
    "ReturnTypes": []
  },
  {
    "ContainingType": "Legno.Api.Controllers.ProjectsController",
    "Method": "Delete",
    "RelativePath": "api/Projects/delete/{id}",
    "HttpMethod": "DELETE",
    "IsController": true,
    "Order": 0,
    "Parameters": [
      {
        "Name": "id",
        "Type": "System.String",
        "IsRequired": true
      }
    ],
    "ReturnTypes": []
  },
  {
    "ContainingType": "Legno.Api.Controllers.ProjectsController",
    "Method": "GetAll",
    "RelativePath": "api/Projects/get-all",
    "HttpMethod": "GET",
    "IsController": true,
    "Order": 0,
    "Parameters": [],
    "ReturnTypes": []
  },
  {
    "ContainingType": "Legno.Api.Controllers.ProjectsController",
    "Method": "Get",
    "RelativePath": "api/Projects/get/{id}",
    "HttpMethod": "GET",
    "IsController": true,
    "Order": 0,
    "Parameters": [
      {
        "Name": "id",
        "Type": "System.String",
        "IsRequired": true
      }
    ],
    "ReturnTypes": []
  },
  {
    "ContainingType": "Legno.Api.Controllers.ProjectsController",
    "Method": "Reorder",
    "RelativePath": "api/Projects/reorder",
    "HttpMethod": "POST",
    "IsController": true,
    "Order": 0,
    "Parameters": [
      {
        "Name": "items",
        "Type": "System.Collections.Generic.List\u00601[[Legno.Application.Dtos.Project.ProjectReorderDto, Legno.Application, Version=1.0.0.0, Culture=neutral, PublicKeyToken=null]]",
        "IsRequired": true
      }
    ],
    "ReturnTypes": []
  },
  {
    "ContainingType": "Legno.Api.Controllers.ProjectsController",
    "Method": "Update",
    "RelativePath": "api/Projects/update",
    "HttpMethod": "PUT",
    "IsController": true,
    "Order": 0,
    "Parameters": [
      {
        "Name": "Id",
        "Type": "System.String",
        "IsRequired": false
      },
      {
        "Name": "Title",
        "Type": "System.String",
        "IsRequired": false
      },
      {
        "Name": "TitleEng",
        "Type": "System.String",
        "IsRequired": false
      },
      {
        "Name": "TitleRu",
        "Type": "System.String",
        "IsRequired": false
      },
      {
        "Name": "SubTitle",
        "Type": "System.String",
        "IsRequired": false
      },
      {
        "Name": "SubTitleEng",
        "Type": "System.String",
        "IsRequired": false
      },
      {
        "Name": "SubTitleRu",
        "Type": "System.String",
        "IsRequired": false
      },
      {
        "Name": "CardImage",
        "Type": "Microsoft.AspNetCore.Http.IFormFile",
        "IsRequired": false
      },
      {
        "Name": "TeamId",
        "Type": "System.String",
        "IsRequired": false
      },
      {
        "Name": "DeleteImageNames",
        "Type": "System.Collections.Generic.List\u00601[[System.String, System.Private.CoreLib, Version=8.0.0.0, Culture=neutral, PublicKeyToken=7cec85d7bea7798e]]",
        "IsRequired": false
      },
      {
        "Name": "DeleteVideoNames",
        "Type": "System.Collections.Generic.List\u00601[[System.String, System.Private.CoreLib, Version=8.0.0.0, Culture=neutral, PublicKeyToken=7cec85d7bea7798e]]",
        "IsRequired": false
      },
      {
        "Name": "DeleteFabricIds",
        "Type": "System.Collections.Generic.List\u00601[[System.String, System.Private.CoreLib, Version=8.0.0.0, Culture=neutral, PublicKeyToken=7cec85d7bea7798e]]",
        "IsRequired": false
      },
      {
        "Name": "DeleteSliderImageNames",
        "Type": "System.Collections.Generic.List\u00601[[System.String, System.Private.CoreLib, Version=8.0.0.0, Culture=neutral, PublicKeyToken=7cec85d7bea7798e]]",
        "IsRequired": false
      },
      {
        "Name": "CategoryId",
        "Type": "System.String",
        "IsRequired": false
      },
      {
        "Name": "ProjectImages",
        "Type": "System.Collections.Generic.List\u00601[[Microsoft.AspNetCore.Http.IFormFile, Microsoft.AspNetCore.Http.Features, Version=8.0.0.0, Culture=neutral, PublicKeyToken=adb9793829ddae60]]",
        "IsRequired": false
      },
      {
        "Name": "ProjectSliderImages",
        "Type": "System.Collections.Generic.List\u00601[[Microsoft.AspNetCore.Http.IFormFile, Microsoft.AspNetCore.Http.Features, Version=8.0.0.0, Culture=neutral, PublicKeyToken=adb9793829ddae60]]",
        "IsRequired": false
      },
      {
        "Name": "ProjectVideos",
        "Type": "System.Collections.Generic.List\u00601[[System.String, System.Private.CoreLib, Version=8.0.0.0, Culture=neutral, PublicKeyToken=7cec85d7bea7798e]]",
        "IsRequired": false
      },
      {
        "Name": "FabricIds",
        "Type": "System.Collections.Generic.List\u00601[[System.String, System.Private.CoreLib, Version=8.0.0.0, Culture=neutral, PublicKeyToken=7cec85d7bea7798e]]",
        "IsRequired": false
      }
    ],
    "ReturnTypes": []
  },
  {
    "ContainingType": "Legno.Api.Controllers.SearchController",
    "Method": "SearchProjects",
    "RelativePath": "api/Search/projects",
    "HttpMethod": "GET",
    "IsController": true,
    "Order": 0,
    "Parameters": [
      {
        "Name": "q",
        "Type": "System.String",
        "IsRequired": false
      }
    ],
    "ReturnTypes": []
  },
  {
    "ContainingType": "Legno.WebApi.Controllers.SliderServicesController",
    "Method": "Delete",
    "RelativePath": "api/SliderServices/delete/{ServiceSliderId}",
    "HttpMethod": "DELETE",
    "IsController": true,
    "Order": 0,
    "Parameters": [
      {
        "Name": "ServiceSliderId",
        "Type": "System.String",
        "IsRequired": true
      }
    ],
    "ReturnTypes": []
  },
  {
    "ContainingType": "Legno.WebApi.Controllers.SliderServicesController",
    "Method": "GetAll",
    "RelativePath": "api/SliderServices/get-all",
    "HttpMethod": "GET",
    "IsController": true,
    "Order": 0,
    "Parameters": [],
    "ReturnTypes": []
  },
  {
    "ContainingType": "Legno.WebApi.Controllers.SliderServicesController",
    "Method": "Get",
    "RelativePath": "api/SliderServices/get/{ServiceSliderId}",
    "HttpMethod": "GET",
    "IsController": true,
    "Order": 0,
    "Parameters": [
      {
        "Name": "ServiceSliderId",
        "Type": "System.String",
        "IsRequired": true
      }
    ],
    "ReturnTypes": []
  },
  {
    "ContainingType": "Legno.WebApi.Controllers.SliderServicesController",
    "Method": "Upload",
    "RelativePath": "api/SliderServices/upload",
    "HttpMethod": "POST",
    "IsController": true,
    "Order": 0,
    "Parameters": [
      {
        "Name": "ServiceSliderName",
        "Type": "Microsoft.AspNetCore.Http.IFormFile",
        "IsRequired": false
      }
    ],
    "ReturnTypes": []
  },
  {
    "ContainingType": "Legno.Api.Controllers.SubscribersController",
    "Method": "CreateSubscriber",
    "RelativePath": "api/Subscribers/create-subscriber",
    "HttpMethod": "POST",
    "IsController": true,
    "Order": 0,
    "Parameters": [
      {
        "Name": "request",
        "Type": "Legno.Api.Controllers.SubscribersController\u002BAddSubscriberRequest",
        "IsRequired": true
      }
    ],
    "ReturnTypes": []
  },
  {
    "ContainingType": "Legno.Api.Controllers.SubscribersController",
    "Method": "DeleteSubscriber",
    "RelativePath": "api/Subscribers/delete-subscriber/{subscriberName}",
    "HttpMethod": "DELETE",
    "IsController": true,
    "Order": 0,
    "Parameters": [
      {
        "Name": "subscriberName",
        "Type": "System.String",
        "IsRequired": true
      }
    ],
    "ReturnTypes": []
  },
  {
    "ContainingType": "Legno.Api.Controllers.SubscribersController",
    "Method": "GetAllSubscribers",
    "RelativePath": "api/Subscribers/get-all-subscribers",
    "HttpMethod": "GET",
    "IsController": true,
    "Order": 0,
    "Parameters": [],
    "ReturnTypes": []
  },
  {
    "ContainingType": "Legno.Api.Controllers.TeamsController",
    "Method": "CreateTeam",
    "RelativePath": "api/Teams/create-team",
    "HttpMethod": "POST",
    "IsController": true,
    "Order": 0,
    "Parameters": [
      {
        "Name": "Name",
        "Type": "System.String",
        "IsRequired": false
      },
      {
        "Name": "NameRu",
        "Type": "System.String",
        "IsRequired": false
      },
      {
        "Name": "NameEng",
        "Type": "System.String",
        "IsRequired": false
      },
      {
        "Name": "Surname",
        "Type": "System.String",
        "IsRequired": false
      },
      {
        "Name": "SurnameEng",
        "Type": "System.String",
        "IsRequired": false
      },
      {
        "Name": "SurnameRu",
        "Type": "System.String",
        "IsRequired": false
      },
      {
        "Name": "Position",
        "Type": "System.String",
        "IsRequired": false
      },
      {
        "Name": "PositionEng",
        "Type": "System.String",
        "IsRequired": false
      },
      {
        "Name": "PositionRu",
        "Type": "System.String",
        "IsRequired": false
      },
      {
        "Name": "CardImage",
        "Type": "Microsoft.AspNetCore.Http.IFormFile",
        "IsRequired": false
      },
      {
        "Name": "InstagramLink",
        "Type": "System.String",
        "IsRequired": false
      },
      {
        "Name": "LinkedInLink",
        "Type": "System.String",
        "IsRequired": false
      }
    ],
    "ReturnTypes": []
  },
  {
    "ContainingType": "Legno.Api.Controllers.TeamsController",
    "Method": "DeleteTeam",
    "RelativePath": "api/Teams/delete-team/{teamId}",
    "HttpMethod": "DELETE",
    "IsController": true,
    "Order": 0,
    "Parameters": [
      {
        "Name": "teamId",
        "Type": "System.String",
        "IsRequired": true
      }
    ],
    "ReturnTypes": []
  },
  {
    "ContainingType": "Legno.Api.Controllers.TeamsController",
    "Method": "GetAllTeams",
    "RelativePath": "api/Teams/get-all-teams",
    "HttpMethod": "GET",
    "IsController": true,
    "Order": 0,
    "Parameters": [],
    "ReturnTypes": []
  },
  {
    "ContainingType": "Legno.Api.Controllers.TeamsController",
    "Method": "GetTeam",
    "RelativePath": "api/Teams/get-team/{teamId}",
    "HttpMethod": "GET",
    "IsController": true,
    "Order": 0,
    "Parameters": [
      {
        "Name": "teamId",
        "Type": "System.String",
        "IsRequired": true
      }
    ],
    "ReturnTypes": []
  },
  {
    "ContainingType": "Legno.Api.Controllers.TeamsController",
    "Method": "ReorderTeams",
    "RelativePath": "api/Teams/reorder-teams",
    "HttpMethod": "PUT",
    "IsController": true,
    "Order": 0,
    "Parameters": [
      {
        "Name": "orders",
        "Type": "System.Collections.Generic.List\u00601[[Legno.Application.Dtos.Team.TeamOrderUpdateDto, Legno.Application, Version=1.0.0.0, Culture=neutral, PublicKeyToken=null]]",
        "IsRequired": true
      }
    ],
    "ReturnTypes": []
  },
  {
    "ContainingType": "Legno.Api.Controllers.TeamsController",
    "Method": "UpdateTeam",
    "RelativePath": "api/Teams/update-team",
    "HttpMethod": "PUT",
    "IsController": true,
    "Order": 0,
    "Parameters": [
      {
        "Name": "Id",
        "Type": "System.String",
        "IsRequired": false
      },
      {
        "Name": "Name",
        "Type": "System.String",
        "IsRequired": false
      },
      {
        "Name": "NameRu",
        "Type": "System.String",
        "IsRequired": false
      },
      {
        "Name": "NameEng",
        "Type": "System.String",
        "IsRequired": false
      },
      {
        "Name": "Surname",
        "Type": "System.String",
        "IsRequired": false
      },
      {
        "Name": "SurnameEng",
        "Type": "System.String",
        "IsRequired": false
      },
      {
        "Name": "SurnameRu",
        "Type": "System.String",
        "IsRequired": false
      },
      {
        "Name": "Position",
        "Type": "System.String",
        "IsRequired": false
      },
      {
        "Name": "PositionEng",
        "Type": "System.String",
        "IsRequired": false
      },
      {
        "Name": "PositionRu",
        "Type": "System.String",
        "IsRequired": false
      },
      {
        "Name": "CardImage",
        "Type": "Microsoft.AspNetCore.Http.IFormFile",
        "IsRequired": false
      },
      {
        "Name": "InstagramLink",
        "Type": "System.String",
        "IsRequired": false
      },
      {
        "Name": "LinkedInLink",
        "Type": "System.String",
        "IsRequired": false
      }
    ],
    "ReturnTypes": []
  },
  {
    "ContainingType": "Legno.Api.Controllers.UserProjectsController",
    "Method": "Create",
    "RelativePath": "api/UserProjects/create",
    "HttpMethod": "POST",
    "IsController": true,
    "Order": 0,
    "Parameters": [
      {
        "Name": "ProjectFileName",
        "Type": "Microsoft.AspNetCore.Http.IFormFile",
        "IsRequired": false
      },
      {
        "Name": "PhoneNumber",
        "Type": "System.String",
        "IsRequired": false
      },
      {
        "Name": "Description",
        "Type": "System.String",
        "IsRequired": false
      }
    ],
    "ReturnTypes": []
  },
  {
    "ContainingType": "Legno.Api.Controllers.UserProjectsController",
    "Method": "Delete",
    "RelativePath": "api/UserProjects/delete/{id}",
    "HttpMethod": "DELETE",
    "IsController": true,
    "Order": 0,
    "Parameters": [
      {
        "Name": "id",
        "Type": "System.String",
        "IsRequired": true
      }
    ],
    "ReturnTypes": []
  },
  {
    "ContainingType": "Legno.Api.Controllers.UserProjectsController",
    "Method": "GetAll",
    "RelativePath": "api/UserProjects/get-all",
    "HttpMethod": "GET",
    "IsController": true,
    "Order": 0,
    "Parameters": [],
    "ReturnTypes": []
  },
  {
    "ContainingType": "Legno.Api.Controllers.UserProjectsController",
    "Method": "Get",
    "RelativePath": "api/UserProjects/get/{id}",
    "HttpMethod": "GET",
    "IsController": true,
    "Order": 0,
    "Parameters": [
      {
        "Name": "id",
        "Type": "System.String",
        "IsRequired": true
      }
    ],
    "ReturnTypes": []
  },
  {
    "ContainingType": "Legno.Api.Controllers.UserProjectsController",
    "Method": "Update",
    "RelativePath": "api/UserProjects/update",
    "HttpMethod": "PUT",
    "IsController": true,
    "Order": 0,
    "Parameters": [
      {
        "Name": "Id",
        "Type": "System.String",
        "IsRequired": false
      },
      {
        "Name": "ProjectFileName",
        "Type": "Microsoft.AspNetCore.Http.IFormFile",
        "IsRequired": false
      },
      {
        "Name": "PhoneNumber",
        "Type": "System.String",
        "IsRequired": false
      },
      {
        "Name": "Description",
        "Type": "System.String",
        "IsRequired": false
      }
    ],
    "ReturnTypes": []
  },
  {
    "ContainingType": "Legno.WebApi.Controllers.WorkPlanningsController",
    "Method": "Create",
    "RelativePath": "api/WorkPlannings/create",
    "HttpMethod": "POST",
    "IsController": true,
    "Order": 0,
    "Parameters": [
      {
        "Name": "dto",
        "Type": "Legno.Application.Dtos.CommonService.CreateCommonServiceDto",
        "IsRequired": true
      }
    ],
    "ReturnTypes": []
  },
  {
    "ContainingType": "Legno.WebApi.Controllers.WorkPlanningsController",
    "Method": "Delete",
    "RelativePath": "api/WorkPlannings/delete/{id}",
    "HttpMethod": "DELETE",
    "IsController": true,
    "Order": 0,
    "Parameters": [
      {
        "Name": "id",
        "Type": "System.String",
        "IsRequired": true
      }
    ],
    "ReturnTypes": []
  },
  {
    "ContainingType": "Legno.WebApi.Controllers.WorkPlanningsController",
    "Method": "GetAll",
    "RelativePath": "api/WorkPlannings/get-all",
    "HttpMethod": "GET",
    "IsController": true,
    "Order": 0,
    "Parameters": [],
    "ReturnTypes": []
  },
  {
    "ContainingType": "Legno.WebApi.Controllers.WorkPlanningsController",
    "Method": "Get",
    "RelativePath": "api/WorkPlannings/get/{id}",
    "HttpMethod": "GET",
    "IsController": true,
    "Order": 0,
    "Parameters": [
      {
        "Name": "id",
        "Type": "System.String",
        "IsRequired": true
      }
    ],
    "ReturnTypes": []
  },
  {
    "ContainingType": "Legno.WebApi.Controllers.WorkPlanningsController",
    "Method": "Update",
    "RelativePath": "api/WorkPlannings/update",
    "HttpMethod": "PUT",
    "IsController": true,
    "Order": 0,
    "Parameters": [
      {
        "Name": "dto",
        "Type": "Legno.Application.Dtos.CommonService.UpdateCommonServiceDto",
        "IsRequired": true
      }
    ],
    "ReturnTypes": []
  }
]